{
  "projects": [
    {
      "title": "Games/Applications",
      "list": [
        {
          "name": "identity quest",
          "type": "game",
          "description": "find your sense of belonging after becoming disoriented",
          "date": "feb 2024",
          "image": "/images/identity_quest.png",
          "link": "#"
        },
        {
          "name": "seashell scavenger",
          "type": "game",
          "description": "relax and collect seashells",
          "date": "jan 2024",
          "image": "/images/shoreline_scavenger.png",
          "link": "#"
        },
        { 
          "name": "cake",
          "type": "game",
          "description": "catch ingredients to make a cake for your mom",
          "date": "dec 2023",
          "image": "/images/cake.png",
          "link": "#"

      },
        {
          "name": "origami workshop",
          "type": "game",
          "description": "craft, learn, and create paper figures",
          "date": "nov 2023",
          "image": "",
          "link": "#"
        },
        {
          "name": "drawing tool",
          "type": "game",
          "description": "create simple drawings with this pastel drawing tool",
          "date": "oct 2023",
          "image": "",
          "link": "#"
        },
        {
          "name": "bunny puzzles",
          "type": "game",
          "description": "collect unique bunnies by completing colorful puzzles in different biomes ",
          "date": "oct 2023",
          "image": "/images/bunnygame.png",
          "link": "#"
        },
        {


        }
      ]
    },
    {
      "title": "3D Models",
      "list": [
        {
          "name": "cliff",
          "type": "3d models",
          "description": "poly cliff scene i created for a vr game i worked on ",
          "date": "march 2024",
          "image": "",
          "link": "#"
        },
        {
          "name": "chess board",
          "type": "3d models",
          "description": "pink lemonade chess board",
          "date": "aug 2021",
          "image": "/images/chessboard.png",
          "link": "#"
        },
        {
          "name": "macaroons",
          "type": "3d models",
          "description": "plate of macaroons",
          "date": "nov 2021",
          "image": "/images/macaroons.png",
          "link": "#"
        },
        {
          "name": "fidget cube",
          "type": "3d models",
          "description": "fidget cube made in blender",
          "date": "jan 2022",
          "image": "/images/fidget_cube.png",
          "link": "#"
        },
        {
          "name": "sushi",
          "type": "3d models",
          "description": "salmon nigiri on wood plate",
          "date": "dec 2021",
          "image": "/images/sushi.png",
          "link": "#"
        },
        {
        

        }  
      ] 
    },
    {
      "title": "Digital Paintings",
      "list": [
        {
            "name": "shapes",
            "type": "digital paintings",
            "description": "abstract shapes",
            "date": "jan 2022",
            "image": "/images/abstract_shapes.jpg",
            "link": "#"
          },
          {
            "name": "love",
            "type": "digital paintings",
            "description": "two paper people holding hands",
            "date": "feb 2022",
            "image": "/images/love.jpg",
            "link": "#"
          },
          {
            "name": "rainbow",
            "type": "digital paintings",
            "description": "rainbow abstract shapes",
            "date": "march 2022",
            "image": "/images/rainbow.jpg",
            "link": "#"
          },
          {
            "name": "confetti",
            "type": "digital paintings",
            "description": "angel bunny surrounded by abstract balloons and confetti",
            "date": "april 2022",
            "image": "/images/angel.jpg",
            "link": "#"
          },
          {
            "name": "planet",
            "type": "digital paintings",
            "description": "A black and white planet",
            "date": "jan 2023",
            "image": "/images/planet.jpg",
            "link": "#"

          }
      ]
    },
    {
      "title": "Posters",
      "list": [  
      {
        "name": "confidence",
        "type": "posters",
        "description": "poster adorned with positive words alongside pictures of Yeji from ITZY",
        "date": "jan 2022",
        "image": "/images/confidence.jpg",
        "link": "#"
      },
        {
          "name": "think before you drink",
        "type": "posters",
        "description": "alcoholism awareness poster",
        "date": "feb 2022",
        "image": "/images/thinkbeforeyoudrink.jpg",
        "link": "#"
        },
        { 
          "name": "stay hydrated",
          "type": "posters",
          "description": "hydration poster",
          "date": "march 2022",
          "image": "/images/stayhydrated.png",
          "link": "#"
        },
        { 
          "name": "calluna",
          "type": "posters",
          "description": "typeface poster featuring the font Calluna",
          "date": "april 2022",
          "image": "/images/calluna.png",
          "link": "#"
        },
        {
          "name": "bitcount",
          "type": "posters",
          "description": "typeface poster featuring the font Bitcount Grid Double",
          "date": "may 2022",
          "image": "/images/bitcount.png",
          "link": "#"
        }
      ]
    },
    {
        "title": "Other Works",
        "list": [
        {
          "name": "letters, textures, words, patterns, & lights",
          "type": "other works",
          "description": "photography poster",
          "date": "may 2022",
          "image": "",
          "link": "#"

        },
        {
          "name": "sparkles",
          "type": "other works",
          "description": "twitch overlay",
          "date": "march 2023",
          "image": "/images/overlay.jpg",
          "link": "#"
        },
        {
          "name": "butterfly hug",
          "type": "other works",
          "description": "butterfly russian doll made out of wood and acrylic paint",
          "date": "sep 2021",
          "image": "/images/russiandoll.jpg",
          "link": "#"
        },
        {
          "name": "mari",
          "type": "other works",
          "description": "twitch banner",
          "date": "sep 2021",
          "image": "/images/mari.png",
          "link": "#"
        }
      ]
    }
  ]
}